<?xml version="1.0" encoding="utf-8"?>
<TextureAtlas imagePath="horsebf.png">
	<!-- Created with Adobe Animate version 20.0.2.22168 -->
	<!-- http://www.adobe.com/products/animate.html -->
	<SubTexture name="dmiss 10000" x="392" y="0" width="397" height="437" frameX="-10" frameY="0" frameWidth="416" frameHeight="437"/>
	<SubTexture name="dmiss 10001" x="1583" y="0" width="416" height="416" frameX="0" frameY="-19" frameWidth="416" frameHeight="437"/>
	<SubTexture name="dmiss 10002" x="789" y="0" width="397" height="437" frameX="-10" frameY="0" frameWidth="416" frameHeight="437"/>
	<SubTexture name="dmiss 10003" x="789" y="0" width="397" height="437" frameX="-10" frameY="0" frameWidth="416" frameHeight="437"/>
	<SubTexture name="dmiss 10004" x="789" y="0" width="397" height="437" frameX="-10" frameY="0" frameWidth="416" frameHeight="437"/>
	<SubTexture name="dmiss 10005" x="789" y="0" width="397" height="437" frameX="-10" frameY="0" frameWidth="416" frameHeight="437"/>
	<SubTexture name="dmiss 10006" x="789" y="0" width="397" height="437" frameX="-10" frameY="0" frameWidth="416" frameHeight="437"/>
	<SubTexture name="dmiss 10007" x="789" y="0" width="397" height="437" frameX="-10" frameY="0" frameWidth="416" frameHeight="437"/>
	<SubTexture name="dmiss 10008" x="789" y="0" width="397" height="437" frameX="-10" frameY="0" frameWidth="416" frameHeight="437"/>
	<SubTexture name="dmiss 10009" x="789" y="0" width="397" height="437" frameX="-10" frameY="0" frameWidth="416" frameHeight="437"/>
	<SubTexture name="down 10000" x="1186" y="0" width="397" height="437" frameX="0" frameY="-8" frameWidth="397" frameHeight="450"/>
	<SubTexture name="down 10001" x="0" y="0" width="392" height="446" frameX="0" frameY="-1" frameWidth="397" frameHeight="450"/>
	<SubTexture name="down 10002" x="0" y="0" width="392" height="446" frameX="0" frameY="-1" frameWidth="397" frameHeight="450"/>
	<SubTexture name="down 10003" x="1583" y="416" width="375" height="450" frameX="-14" frameY="0" frameWidth="397" frameHeight="450"/>
	<SubTexture name="down 10004" x="1583" y="416" width="375" height="450" frameX="-14" frameY="0" frameWidth="397" frameHeight="450"/>
	<SubTexture name="down 10005" x="3145" y="0" width="379" height="449" frameX="-12" frameY="0" frameWidth="397" frameHeight="450"/>
	<SubTexture name="down 10006" x="3145" y="0" width="379" height="449" frameX="-12" frameY="0" frameWidth="397" frameHeight="450"/>
	<SubTexture name="down 10007" x="3145" y="0" width="379" height="449" frameX="-12" frameY="0" frameWidth="397" frameHeight="450"/>
	<SubTexture name="down 10008" x="3145" y="0" width="379" height="449" frameX="-12" frameY="0" frameWidth="397" frameHeight="450"/>
	<SubTexture name="down 10009" x="3145" y="0" width="379" height="449" frameX="-12" frameY="0" frameWidth="397" frameHeight="450"/>
	<SubTexture name="idle 10000" x="684" y="868" width="344" height="446" frameX="0" frameY="-6" frameWidth="356" frameHeight="453"/>
	<SubTexture name="idle 10001" x="2983" y="918" width="344" height="437" frameX="0" frameY="-15" frameWidth="356" frameHeight="453"/>
	<SubTexture name="idle 10002" x="2983" y="918" width="344" height="437" frameX="0" frameY="-15" frameWidth="356" frameHeight="453"/>
	<SubTexture name="idle 10003" x="1894" y="918" width="344" height="442" frameX="-6" frameY="-11" frameWidth="356" frameHeight="453"/>
	<SubTexture name="idle 10004" x="1894" y="918" width="344" height="442" frameX="-6" frameY="-11" frameWidth="356" frameHeight="453"/>
	<SubTexture name="idle 10005" x="1549" y="866" width="345" height="453" frameX="-11" frameY="0" frameWidth="356" frameHeight="453"/>
	<SubTexture name="idle 10006" x="1549" y="866" width="345" height="453" frameX="-11" frameY="0" frameWidth="356" frameHeight="453"/>
	<SubTexture name="idle 10007" x="343" y="868" width="341" height="450" frameX="-14" frameY="-3" frameWidth="356" frameHeight="453"/>
	<SubTexture name="idle 10008" x="343" y="868" width="341" height="450" frameX="-14" frameY="-3" frameWidth="356" frameHeight="453"/>
	<SubTexture name="idle 10009" x="343" y="868" width="341" height="450" frameX="-14" frameY="-3" frameWidth="356" frameHeight="453"/>
	<SubTexture name="idle 10010" x="343" y="868" width="341" height="450" frameX="-14" frameY="-3" frameWidth="356" frameHeight="453"/>
	<SubTexture name="idle 10011" x="343" y="868" width="341" height="450" frameX="-14" frameY="-3" frameWidth="356" frameHeight="453"/>
	<SubTexture name="idle 10012" x="343" y="868" width="341" height="450" frameX="-14" frameY="-3" frameWidth="356" frameHeight="453"/>
	<SubTexture name="idle 10013" x="343" y="868" width="341" height="450" frameX="-14" frameY="-3" frameWidth="356" frameHeight="453"/>
	<SubTexture name="left 10000" x="781" y="437" width="389" height="431" frameX="0" frameY="-27" frameWidth="393" frameHeight="460"/>
	<SubTexture name="left 10001" x="1170" y="437" width="379" height="437" frameX="-7" frameY="-22" frameWidth="393" frameHeight="460"/>
	<SubTexture name="left 10002" x="1170" y="437" width="379" height="437" frameX="-7" frameY="-22" frameWidth="393" frameHeight="460"/>
	<SubTexture name="left 10003" x="2374" y="0" width="374" height="460" frameX="-18" frameY="0" frameWidth="393" frameHeight="460"/>
	<SubTexture name="left 10004" x="2374" y="0" width="374" height="460" frameX="-18" frameY="0" frameWidth="393" frameHeight="460"/>
	<SubTexture name="left 10005" x="3524" y="0" width="378" height="450" frameX="-15" frameY="-9" frameWidth="393" frameHeight="460"/>
	<SubTexture name="left 10006" x="3524" y="0" width="378" height="450" frameX="-15" frameY="-9" frameWidth="393" frameHeight="460"/>
	<SubTexture name="left 10007" x="3524" y="0" width="378" height="450" frameX="-15" frameY="-9" frameWidth="393" frameHeight="460"/>
	<SubTexture name="left 10008" x="3524" y="0" width="378" height="450" frameX="-15" frameY="-9" frameWidth="393" frameHeight="460"/>
	<SubTexture name="left 10009" x="3524" y="0" width="378" height="450" frameX="-15" frameY="-9" frameWidth="393" frameHeight="460"/>
	<SubTexture name="lmiss 10000" x="2748" y="431" width="389" height="431" frameX="-7" frameY="0" frameWidth="397" frameHeight="431"/>
	<SubTexture name="lmiss 10001" x="2748" y="0" width="397" height="431"/>
	<SubTexture name="lmiss 10002" x="392" y="437" width="389" height="431" frameX="-7" frameY="0" frameWidth="397" frameHeight="431"/>
	<SubTexture name="lmiss 10003" x="392" y="437" width="389" height="431" frameX="-7" frameY="0" frameWidth="397" frameHeight="431"/>
	<SubTexture name="lmiss 10004" x="392" y="437" width="389" height="431" frameX="-7" frameY="0" frameWidth="397" frameHeight="431"/>
	<SubTexture name="lmiss 10005" x="392" y="437" width="389" height="431" frameX="-7" frameY="0" frameWidth="397" frameHeight="431"/>
	<SubTexture name="lmiss 10006" x="392" y="437" width="389" height="431" frameX="-7" frameY="0" frameWidth="397" frameHeight="431"/>
	<SubTexture name="lmiss 10007" x="392" y="437" width="389" height="431" frameX="-7" frameY="0" frameWidth="397" frameHeight="431"/>
	<SubTexture name="lmiss 10008" x="392" y="437" width="389" height="431" frameX="-7" frameY="0" frameWidth="397" frameHeight="431"/>
	<SubTexture name="lmiss 10009" x="392" y="437" width="389" height="431" frameX="-7" frameY="0" frameWidth="397" frameHeight="431"/>
	<SubTexture name="right 10000" x="2561" y="1308" width="323" height="448" frameX="-1" frameY="-2" frameWidth="328" frameHeight="450"/>
	<SubTexture name="right 10001" x="336" y="1318" width="317" height="441" frameX="-11" frameY="-8" frameWidth="328" frameHeight="450"/>
	<SubTexture name="right 10002" x="336" y="1318" width="317" height="441" frameX="-11" frameY="-8" frameWidth="328" frameHeight="450"/>
	<SubTexture name="right 10003" x="3327" y="918" width="323" height="449" frameX="0" frameY="0" frameWidth="328" frameHeight="450"/>
	<SubTexture name="right 10004" x="3327" y="918" width="323" height="449" frameX="0" frameY="0" frameWidth="328" frameHeight="450"/>
	<SubTexture name="right 10005" x="684" y="1314" width="322" height="448" frameX="0" frameY="-1" frameWidth="328" frameHeight="450"/>
	<SubTexture name="right 10006" x="684" y="1314" width="322" height="448" frameX="0" frameY="-1" frameWidth="328" frameHeight="450"/>
	<SubTexture name="right 10007" x="684" y="1314" width="322" height="448" frameX="0" frameY="-1" frameWidth="328" frameHeight="450"/>
	<SubTexture name="right 10008" x="684" y="1314" width="322" height="448" frameX="0" frameY="-1" frameWidth="328" frameHeight="450"/>
	<SubTexture name="right 10009" x="684" y="1314" width="322" height="448" frameX="0" frameY="-1" frameWidth="328" frameHeight="450"/>
	<SubTexture name="rmiss 10000" x="3650" y="918" width="323" height="448" frameX="0" frameY="0" frameWidth="342" frameHeight="448"/>
	<SubTexture name="rmiss 10001" x="0" y="915" width="336" height="440" frameX="-6" frameY="-7" frameWidth="342" frameHeight="448"/>
	<SubTexture name="rmiss 10002" x="2238" y="942" width="323" height="448" frameX="0" frameY="0" frameWidth="342" frameHeight="448"/>
	<SubTexture name="rmiss 10003" x="2238" y="942" width="323" height="448" frameX="0" frameY="0" frameWidth="342" frameHeight="448"/>
	<SubTexture name="rmiss 10004" x="2238" y="942" width="323" height="448" frameX="0" frameY="0" frameWidth="342" frameHeight="448"/>
	<SubTexture name="rmiss 10005" x="2238" y="942" width="323" height="448" frameX="0" frameY="0" frameWidth="342" frameHeight="448"/>
	<SubTexture name="rmiss 10006" x="2238" y="942" width="323" height="448" frameX="0" frameY="0" frameWidth="342" frameHeight="448"/>
	<SubTexture name="rmiss 10007" x="2238" y="942" width="323" height="448" frameX="0" frameY="0" frameWidth="342" frameHeight="448"/>
	<SubTexture name="rmiss 10008" x="2238" y="942" width="323" height="448" frameX="0" frameY="0" frameWidth="342" frameHeight="448"/>
	<SubTexture name="rmiss 10009" x="2238" y="942" width="323" height="448" frameX="0" frameY="0" frameWidth="342" frameHeight="448"/>
	<SubTexture name="umiss 10000" x="0" y="446" width="343" height="469" frameX="0" frameY="-13" frameWidth="343" frameHeight="482"/>
	<SubTexture name="umiss 10001" x="2305" y="460" width="327" height="482" frameX="-8" frameY="0" frameWidth="343" frameHeight="482"/>
	<SubTexture name="umiss 10002" x="3137" y="449" width="343" height="469" frameX="0" frameY="-13" frameWidth="343" frameHeight="482"/>
	<SubTexture name="umiss 10003" x="3137" y="449" width="343" height="469" frameX="0" frameY="-13" frameWidth="343" frameHeight="482"/>
	<SubTexture name="umiss 10004" x="3137" y="449" width="343" height="469" frameX="0" frameY="-13" frameWidth="343" frameHeight="482"/>
	<SubTexture name="umiss 10005" x="3137" y="449" width="343" height="469" frameX="0" frameY="-13" frameWidth="343" frameHeight="482"/>
	<SubTexture name="umiss 10006" x="3137" y="449" width="343" height="469" frameX="0" frameY="-13" frameWidth="343" frameHeight="482"/>
	<SubTexture name="umiss 10007" x="3137" y="449" width="343" height="469" frameX="0" frameY="-13" frameWidth="343" frameHeight="482"/>
	<SubTexture name="umiss 10008" x="3137" y="449" width="343" height="469" frameX="0" frameY="-13" frameWidth="343" frameHeight="482"/>
	<SubTexture name="umiss 10009" x="3137" y="449" width="343" height="469" frameX="0" frameY="-13" frameWidth="343" frameHeight="482"/>
	<SubTexture name="up 10000" x="3480" y="450" width="343" height="468" frameX="-37" frameY="0" frameWidth="380" frameHeight="468"/>
	<SubTexture name="up 10001" x="1999" y="0" width="375" height="460" frameX="0" frameY="-6" frameWidth="380" frameHeight="468"/>
	<SubTexture name="up 10002" x="1999" y="0" width="375" height="460" frameX="0" frameY="-6" frameWidth="380" frameHeight="468"/>
	<SubTexture name="up 10003" x="1028" y="874" width="330" height="464" frameX="-32" frameY="-1" frameWidth="380" frameHeight="468"/>
	<SubTexture name="up 10004" x="1028" y="874" width="330" height="464" frameX="-32" frameY="-1" frameWidth="380" frameHeight="468"/>
	<SubTexture name="up 10005" x="2632" y="862" width="351" height="446" frameX="-23" frameY="-20" frameWidth="380" frameHeight="468"/>
	<SubTexture name="up 10006" x="2632" y="862" width="351" height="446" frameX="-23" frameY="-20" frameWidth="380" frameHeight="468"/>
	<SubTexture name="up 10007" x="1958" y="460" width="347" height="458" frameX="-23" frameY="-8" frameWidth="380" frameHeight="468"/>
	<SubTexture name="up 10008" x="1958" y="460" width="347" height="458" frameX="-23" frameY="-8" frameWidth="380" frameHeight="468"/>
	<SubTexture name="up 10009" x="1958" y="460" width="347" height="458" frameX="-23" frameY="-8" frameWidth="380" frameHeight="468"/>
</TextureAtlas>
